nthp_api/__init__.py
nthp_api/cli/__init__.py
nthp_api/cli/logs.py
nthp_api/nthp_build/__init__.py
nthp_api/nthp_build/assets.py
nthp_api/nthp_build/config.py
nthp_api/nthp_build/content.py
nthp_api/nthp_build/database.py
nthp_api/nthp_build/documents.py
nthp_api/nthp_build/dumper.py
nthp_api/nthp_build/fields.py
nthp_api/nthp_build/history.py
nthp_api/nthp_build/loader.py
nthp_api/nthp_build/models.py
nthp_api/nthp_build/parallel.py
nthp_api/nthp_build/people.py
nthp_api/nthp_build/playwrights.py
nthp_api/nthp_build/roles.py
nthp_api/nthp_build/schema.py
nthp_api/nthp_build/search.py
nthp_api/nthp_build/shows.py
nthp_api/nthp_build/smugmug.py
nthp_api/nthp_build/spec.py
nthp_api/nthp_build/trivia.py
nthp_api/nthp_build/venues.py
nthp_api/nthp_build/version.py
nthp_api/nthp_build/years.py
nthp_api/smugmugger/__init__.py
nthp_api/smugmugger/album.py
nthp_api/smugmugger/client.py
nthp_api/smugmugger/config.py
nthp_api/smugmugger/database.py
nthp_api/smugmugger/schema.py
nthp_api/smugmugger/smugmug.py
nthp_api-0.1.8.dist-info/METADATA
nthp_api-0.1.8.dist-info/WHEEL
nthp_api-0.1.8.dist-info/entry_points.txt
nthp_api-0.1.8.dist-info/RECORD
